Metadata-Version: 2.4
Name: melodie-app-django-creator-two
Version: 0.2.0
Summary: Automagically generate Django apps
Author: Mélodie
License: MIT
Requires-Python: >=3.6
License-File: LICENSE
Dynamic: author
Dynamic: license
Dynamic: license-file
Dynamic: requires-python
Dynamic: summary
